{
  "componentName": "rbac.identity",
  "pageName": "rbac",
  "nodeId": "981:86",
  "variantNodeId": "981:74",
  "variantName": "register-default",
  "metadata": {
    "sps.drafts.blockId": "rbac.identity.register-default",
    "sps.drafts.layer": "singlepage",
    "sps.drafts.syncKey": "rbac/models/identity/singlepage/register-default",
    "sps.figma.component": "rbac.identity",
    "sps.figma.variant": "register-default",
    "sps.source.module": "rbac",
    "sps.source.entityType": "model",
    "sps.source.entity": "identity",
    "sps.source.variant": "register-default",
    "sps.contractVersion": "0.1.0",
    "sps.code.component": "apps/drafts/modules/rbac/models/identity/singlepage/register-default/Component.tsx",
    "sps.code.story": "apps/drafts/modules/rbac/models/identity/singlepage/register-default/Component.stories.tsx",
    "sps.figma.nodeId": "981:86",
    "sps.figma.variantNodeId": "981:74",
    "sps.figma.storybookReferenceNodeId": "981:202",
    "sps.storybook.imageCount": "1"
  },
  "storybookReferenceNodeId": "981:202",
  "storybookImageCount": 1
}
