{
  "id": "7bb79498-f35d-482c-8b22-11efe8e8cca0",
  "prevId": "ba4f2b45-6f09-4867-9eda-5e47f2ec42ad",
  "version": "7",
  "dialect": "postgresql",
  "tables": {
    "public.sps_f_s_file": {
      "name": "sps_f_s_file",
      "schema": "",
      "columns": {
        "id": {
          "name": "id",
          "type": "uuid",
          "primaryKey": true,
          "notNull": true,
          "default": "gen_random_uuid()"
        },
        "file": {
          "name": "file",
          "type": "text",
          "primaryKey": false,
          "notNull": true
        },
        "container_class_name": {
          "name": "container_class_name",
          "type": "text",
          "primaryKey": false,
          "notNull": false
        },
        "class_name": {
          "name": "class_name",
          "type": "text",
          "primaryKey": false,
          "notNull": false
        },
        "created_at": {
          "name": "created_at",
          "type": "timestamp",
          "primaryKey": false,
          "notNull": true,
          "default": "now()"
        },
        "updated_at": {
          "name": "updated_at",
          "type": "timestamp",
          "primaryKey": false,
          "notNull": true,
          "default": "now()"
        },
        "variant": {
          "name": "variant",
          "type": "text",
          "primaryKey": false,
          "notNull": true,
          "default": "'default'"
        },
        "admin_title": {
          "name": "admin_title",
          "type": "text",
          "primaryKey": false,
          "notNull": true
        },
        "width": {
          "name": "width",
          "type": "integer",
          "primaryKey": false,
          "notNull": false
        },
        "height": {
          "name": "height",
          "type": "integer",
          "primaryKey": false,
          "notNull": false
        },
        "alt": {
          "name": "alt",
          "type": "text",
          "primaryKey": false,
          "notNull": false
        },
        "size": {
          "name": "size",
          "type": "integer",
          "primaryKey": false,
          "notNull": false
        },
        "extension": {
          "name": "extension",
          "type": "text",
          "primaryKey": false,
          "notNull": false
        },
        "mime_type": {
          "name": "mime_type",
          "type": "text",
          "primaryKey": false,
          "notNull": false
        }
      },
      "indexes": {},
      "foreignKeys": {},
      "compositePrimaryKeys": {},
      "uniqueConstraints": {
        "sps_f_s_file_file_unique": {
          "name": "sps_f_s_file_file_unique",
          "nullsNotDistinct": false,
          "columns": [
            "file"
          ]
        }
      },
      "policies": {},
      "checkConstraints": {},
      "isRLSEnabled": false
    }
  },
  "enums": {},
  "schemas": {},
  "sequences": {},
  "roles": {},
  "policies": {},
  "views": {},
  "_meta": {
    "columns": {},
    "schemas": {},
    "tables": {}
  }
}